activations/__init__.py
activations/activations_hdw.py
activations/activations_sfw.py
core/__init__.py
core/framework.py
layers/__init__.py
layers/base_layer.py
layers/dense_hdw.py
layers/dense_sfw.py
layers/lstm_hdw.py
layers/lstm_sfw.py
preprocessing/__init__.py
preprocessing/quantize.py
DigiNet-0.1.1.dist-info/METADATA
DigiNet-0.1.1.dist-info/WHEEL
DigiNet-0.1.1.dist-info/top_level.txt
DigiNet-0.1.1.dist-info/RECORD
