Metadata-Version: 2.1
Name: DigiNet
Version: 0.1.1
Summary: Digital Simulation for Neural Networks
Home-page: UNKNOWN
Author: Jinhai Hu
Author-email: <jinhai001@e.ntu.edu.sg>
License: UNKNOWN
Keywords: python,Digital Hardwares,Neural Networks
Platform: UNKNOWN
Classifier: Development Status :: 3 - Alpha
Classifier: Intended Audience :: Science/Research
Classifier: Programming Language :: Python :: 3
Classifier: Operating System :: Microsoft :: Windows
